cquai_ml/DatasetSpace.py
cquai_ml/DecisionTreeClassifier.py
cquai_ml/DecisionTreeRegressor.py
cquai_ml/KNeighborsClassifier.py
cquai_ml/LinearDiscriminantAnalysis.py
cquai_ml/LinearRegression.py
cquai_ml/LogisticRegression.py
cquai_ml/UnionHypothesisSpace.py
cquai_ml/__init__.py
cquai_ml-1.0.0.dist-info/METADATA
cquai_ml-1.0.0.dist-info/WHEEL
cquai_ml-1.0.0.dist-info/top_level.txt
cquai_ml-1.0.0.dist-info/RECORD
