Metadata-Version: 2.1
Name: cquai-ml
Version: 1.0.0
Summary: Implement machine learning algorithms with python without sklearn.
Home-page: https://github.com/CQU-AI/ML-Algorithm
Author: CQU-AI
Author-email: peter@mail.loopy.tech
Maintainer: loopyme
Maintainer-email: peter@mail.loopy.tech
License: MIT License
Platform: all
